pyqtjalalidatepicker-0.1.0.dist-info/licenses/LICENSE
qtjalalicomponent/__init__.py
qtjalalicomponent/pyqtjalalidatepicker.py
pyqtjalalidatepicker-0.1.0.dist-info/METADATA
pyqtjalalidatepicker-0.1.0.dist-info/WHEEL
pyqtjalalidatepicker-0.1.0.dist-info/top_level.txt
pyqtjalalidatepicker-0.1.0.dist-info/RECORD
