Metadata-Version: 2.4
Name: pyqtjalalidatepicker
Version: 0.1.0
Summary: A Jalali date picker widget for PyQt5
Home-page: https://github.com/sadng11/pyqt-jalali-date-picker
Author: Sadegh Naghibzadeh
Author-email: sadng11@gmail.com
Classifier: Programming Language :: Python :: 3
Classifier: License :: OSI Approved :: MIT License
Classifier: Operating System :: OS Independent
Requires-Python: >=3.6
License-File: LICENSE
Requires-Dist: PyQt5>=5.15.0
Requires-Dist: jdatetime>=4.2.0
Dynamic: author
Dynamic: author-email
Dynamic: classifier
Dynamic: description
Dynamic: description-content-type
Dynamic: home-page
Dynamic: license-file
Dynamic: requires-dist
Dynamic: requires-python
Dynamic: summary
